README.md
setup.cfg
setup.py
Binomial_and_Gaussian_distributions/Binomialdistribution.py
Binomial_and_Gaussian_distributions/Gaussiandistribution.py
Binomial_and_Gaussian_distributions/Generaldistribution.py
Binomial_and_Gaussian_distributions/__init__.py
Binomial_and_Gaussian_distributions.egg-info/PKG-INFO
Binomial_and_Gaussian_distributions.egg-info/SOURCES.txt
Binomial_and_Gaussian_distributions.egg-info/dependency_links.txt
Binomial_and_Gaussian_distributions.egg-info/not-zip-safe
Binomial_and_Gaussian_distributions.egg-info/top_level.txt