Metadata-Version: 1.0
Name: Binomial-and-Gaussian-distributions
Version: 1.0
Summary: Gaussian_and_Binomial_distributions_package(v1.0)
Home-page: UNKNOWN
Author: UNKNOWN
Author-email: UNKNOWN
License: UNKNOWN
Platform: UNKNOWN
